Workbook
Name Tax_rate: 'DCF model'!$C$26
Name UPDATE: 'Data Sheet (2)'!$E$1
Name UPDATE: #REF!

Sheet Data Sheet (2)
A1: COMPANY NAME | B1: HDFC BANK LTD | E1: =IF(B2<>B3, "A NEW VERSION OF THE WORKSHEET IS AVAILABLE", "")
A2: LATEST VERSION | B2: 2.1 | E2: PLEASE DO NOT MAKE ANY CHANGES TO THIS SHEET
A3: CURRENT VERSION | B3: 2.1
A5: META
A6: Number of shares | B6: =IF(B9>0, B9/B8, 0) -> 1541.8597
A7: Face Value | B7: 1
A8: Current Price | B8: 721.2
A9: Market Capitalization | B9: 1111989.2
A15: PROFIT & LOSS
A16: Report Date | B16: 42825 | C16: 43190 | D16: 43555 | E16: 43921 | F16: 44286 | G16: 44651 | H16: 45016 | I16: 45382 | J16: 45747 | K16: 46112
A17: Sales | B17: 73271.35 | C17: 85287.84 | D17: 105160.74 | E17: 122189.29 | F17: 128552.4 | G17: 135936.41 | H17: 170754.05 | I17: 283649.02 | J17: 336367.43 | K17: 348615.15
A18: Raw Material Cost
A19: Change in Inventory
A20: Power and Fuel
A21: Other Mfr. Exp | B21: 1271.8 | C21: 1314.97 | D21: 1283.53 | E21: 1293.44 | F21: 1649.11 | G21: 1772.27 | H21: 2176.5 | I21: 3255.75 | J21: 3943.56 | K21: 4691.2
A22: Employee Cost | B22: 8508.22 | C22: 9197.15 | D22: 10454.75 | E22: 12924.1 | F22: 13682.35 | G22: 15904.81 | H22: 20031.36 | I22: 31050.07 | J22: 34167.89 | K22: 37645.25
A23: Selling and admin | B23: 3328.39 | C23: 3658.43 | D23: 3900.17 | E23: 4192.15 | F23: 4780.54 | G23: 5406.79 | H23: 6580 | I23: 87580.05 | J23: 105188.45 | K23: 103553.02
A24: Other Expenses | B24: 10747.28 | C24: 15361.71 | D24: 19217.82 | E24: 27049.52 | F24: 32344.53 | G24: 33473.09 | H24: 34254.44 | I24: 52309.67 | J24: 43674.55 | K24: 57745.76
A25: Other Income | B25: 12905.08 | C25: 16056.6 | D25: 18947.05 | E25: 24878.97 | F25: 27332.88 | G25: 31758.99 | H25: 33912.05 | I25: 124345.75 | J25: 134548.5 | K25: 146847.66
A26: Depreciation | B26: 886.19 | C26: 966.78 | D26: 1220.67 | E26: 1276.77 | F26: 1385.01 | G26: 1680.73 | H26: 2345.47 | I26: 3092.08 | J26: 3805.23 | K26: 4194.9
A27: Interest | B27: 38041.58 | C27: 42381.48 | D27: 53712.69 | E27: 62137.42 | F27: 59247.59 | G27: 58584.33 | H27: 77779.94 | I27: 154138.55 | J27: 183894.2 | K27: 185491.23
A28: Profit before tax | B28: 23392.97 | C28: 28463.92 | D28: 34318.16 | E28: 38194.86 | F28: 42796.15 | G28: 50873.38 | H28: 61498.39 | I28: 76568.6 | J28: 96242.05 | K28: 102141.45
A29: Tax | B29: 8078.12 | C29: 9903.08 | D29: 11872.55 | E29: 10898.59 | F29: 10939.38 | G29: 12722.48 | H29: 15349.69 | I29: 11122.1 | J29: 22801.88 | K29: 22921.99
A30: Net profit | B30: 15280.48 | C30: 18510.02 | D30: 22332.43 | E30: 27253.95 | F30: 31833.21 | G30: 38052.75 | H30: 45997.11 | I30: 64062.04 | J30: 70792.25 | K30: 76025.97
A31: Dividend Amount | B31: 2818.8 | C31: 3373.63 | D31: 4084.95 | E31: 1370.82 | F31: 3583.32 | G31: 8595.52 | H31: 10601.43 | I31: 14813.96 | J31: 16834.84 | K31: 23859.77
A40: Quarters
A41: Report Date | B41: 45382 | C41: 45473 | D41: 45565 | E41: 45657 | F41: 45747 | G41: 45838 | H41: 45930 | I41: 46022 | J41: 46112 | K41: 46203
A42: Sales | B42: 79433.61 | C42: 81546.2 | D42: 83001.72 | E42: 85040.17 | F42: 86779.34 | G42: 87371.87 | H42: 86993.84 | I42: 87066.94 | J42: 87182.5 | K42: 90575.33
A43: Expenses | B43: 62938.45 | C43: 49689.62 | D43: 52074.11 | E43: 41306.79 | F43: 47709.16 | G43: 64496.63 | H43: 45160.88 | I43: 54144.75 | J43: 44027.87 | K43: 58291.57
A44: Other Income | B44: 44957.74 | C44: 35450.29 | D44: 38455.02 | E44: 27153.77 | F44: 33489.42 | G44: 45683.1 | H44: 31566.79 | I44: 39860.33 | J44: 29737.44 | K44: 42535.03
A45: Depreciation
A46: Interest | B46: 43691.51 | C46: 44579.5 | D46: 45414.21 | E46: 46914.28 | F46: 46986.21 | G46: 47708.51 | H46: 46740.86 | I46: 45821.42 | J46: 45220.44 | K46: 47625.63
A47: Profit before tax | B47: 17761.39 | C47: 22727.37 | D47: 23968.42 | E47: 23972.87 | F47: 25573.39 | G47: 20849.83 | H47: 26658.89 | I47: 26961.1 | J47: 27671.63 | K47: 27193.16
A48: Tax | B48: -251.48 | C48: 5539.32 | D48: 5340.98 | E48: 5632.76 | F48: 6288.82 | G48: 3759.4 | H48: 6295.12 | I48: 6270.06 | J48: 6597.41 | K48: 6810.47
A49: Net profit | B49: 17622.38 | C49: 16474.85 | D49: 17825.91 | E49: 17656.61 | F49: 18834.88 | G49: 16257.91 | H49: 19610.67 | I49: 19806.63 | J49: 20350.76 | K49: 19244.71
A50: Operating Profit | B50: 16495.16 | C50: 31856.58 | D50: 30927.61 | E50: 43733.38 | F50: 39070.18 | G50: 22875.24 | H50: 41832.96 | I50: 32922.19 | J50: 43154.63 | K50: 32283.76
A55: BALANCE SHEET
A56: Report Date | B56: 42825 | C56: 43190 | D56: 43555 | E56: 43921 | F56: 44286 | G56: 44651 | H56: 45016 | I56: 45382 | J56: 45747 | K56: 46112
A57: Equity Share Capital | B57: 512.51 | C57: 519.02 | D57: 544.66 | E57: 548.33 | F57: 551.28 | G57: 554.55 | H57: 557.97 | I57: 759.69 | J57: 765.22 | K57: 1539.34
A58: Reserves | B58: 91281.44 | C58: 109080.11 | D58: 153128 | E58: 175810.38 | F58: 209258.9 | G58: 246771.62 | H58: 288879.53 | I58: 455635.56 | J58: 521024.17 | K58: 584520.13
A59: Borrowings | B59: 741549.89 | C59: 944817.22 | D59: 1080235.5 | E59: 1333041.4 | F59: 1511417.6 | G59: 1784969.5 | H59: 2139211.9 | I59: 3107502.7 | J59: 3345503.8 | K59: 3688122.8
A60: Other Liabilities | B60: 59000.32 | C60: 48769.82 | D60: 58897.59 | E60: 71430.27 | F60: 78278.83 | G60: 90638.6 | H60: 101783.03 | I60: 466296.27 | J60: 524816.64 | K60: 633519.03
A61: Total | B61: 892344.16 | C61: 1103186.2 | D61: 1292805.7 | E61: 1580830.4 | F61: 1799506.6 | G61: 2122934.3 | H61: 2530432.4 | I61: 4030194.3 | J61: 4392109.8 | K61: 4907701.3
A62: Net Block | B62: 3999.7 | C62: 4008.13 | D62: 4368.63 | E62: 4775.65 | F62: 5248.35 | G62: 6432.07 | H62: 8431.35 | I62: 12603.76 | J62: 15257.94 | K62: 16491.59
A63: Capital Work in Progress
A64: Investments | B64: 210777.11 | C64: 238460.92 | D64: 289445.87 | E64: 389304.95 | F64: 438823.11 | G64: 449263.86 | H64: 511581.71 | I64: 1005681.6 | J64: 1186472.9 | K64: 1280216.3
A65: Other Assets | B65: 677567.35 | C65: 860717.12 | D65: 998991.21 | E65: 1186749.8 | F65: 1355435.2 | G65: 1667238.4 | H65: 2010419.4 | I65: 3011908.9 | J65: 3190379 | K65: 3610993.5
A66: Total | B66: 892344.16 | C66: 1103186.2 | D66: 1292805.7 | E66: 1580830.4 | F66: 1799506.6 | G66: 2122934.3 | H66: 2530432.4 | I66: 4030194.3 | J66: 4392109.8 | K66: 4907701.3
A67: Receivables
A68: Inventory
A69: Cash & Bank | B69: 37910.55 | C69: 104688.2 | D69: 46804.59 | E69: 72211 | F69: 97370.35 | G69: 130030.71 | H69: 117189.28 | I69: 178718.67 | J69: 144390.25 | K69: 200707.11
A70: No. of Equity Shares | B70: 2562545717 | C70: 2595090267 | D70: 2723306610 | E70: 5483286460 | F70: 5512776482 | G70: 5545540976 | H70: 5579742786 | I70: 7596910662 | J70: 7652221674 | K70: 15393368328
A71: New Bonus Shares
A72: Face value | B72: 2 | C72: 2 | D72: 2 | E72: 1 | F72: 1 | G72: 1 | H72: 1 | I72: 1 | J72: 1 | K72: 1
A80: CASH FLOW:
A81: Report Date | B81: 42825 | C81: 43190 | D81: 43555 | E81: 43921 | F81: 44286 | G81: 44651 | H81: 45016 | I81: 45382 | J81: 45747 | K81: 46112
A82: Cash from Operating Activity | B82: 17281.59 | C82: 17214.38 | D82: -62871.54 | E82: -16869.09 | F82: 42476.45 | G82: -11959.57 | H82: 20813.7 | I82: 19069.34 | J82: 127241.84 | K82: 113506.38
A83: Cash from Investing Activity | B83: -1146.38 | C83: -841.6 | D83: -1503.06 | E83: -1402.94 | F83: -1822.7 | G83: -2051.23 | H83: -2992.18 | I83: 16600.42 | J83: -3650.91 | K83: 7476.62
A84: Cash from Financing Activity | B84: -5892.97 | C84: 57377.66 | D84: 23130.69 | E84: 24394.5 | F84: -7321.35 | G84: 48124.02 | H84: 23940.56 | I84: -3983.06 | J84: -102477.54 | K84: -59004.85
A85: Net Cash Flow | B85: 10242.24 | C85: 73750.44 | D85: -41243.91 | E85: 6122.47 | F85: 33332.4 | G85: 34113.22 | H85: 41762.08 | I85: 31686.7 | J85: 21113.39 | K85: 61978.15
I86: =SUM(H67:H68)-SUM(I67:I68) -> 0 | J86: =SUM(I67:I68)-SUM(J67:J68) -> 0 | K86: =SUM(J67:J68)-SUM(K67:K68) -> 0
I87: =I86+I83 -> 16600.42 | J87: =J86+J83 -> -3650.91 | K87: =K86+K83 -> 7476.62
A88: NOPAT | I88: ='DCF model'!D48*(1-Tax_rate) -> 79771.05 | J88: ='DCF model'!E48*(1-Tax_rate) -> 109190.81 | K88: ='DCF model'!F48*(1-Tax_rate) -> 105588.76
I89: =I88/I87 -> 4.8053634 | J89: =J88/J87 -> -29.907835 | K89: =K88/K87 -> 14.122527
A92: PRICE: | B92: 360.64 | C92: 471.53 | D92: 579.73 | E92: 430.95 | F92: 746.83 | G92: 735.18 | H92: 804.78 | I92: 723.95 | J92: 914.1 | K92: 731.55
A94: DERIVED:
A95: Adjusted Equity Shares in Cr | B95: 1025.02 | C95: 1038.04 | D95: 1089.32 | E95: 1096.66 | F95: 1102.56 | G95: 1109.11 | H95: 1115.95 | I95: 1519.38 | J95: 1530.44 | K95: 1539.34

Sheet DCF model
A1: DISCOUNTED CASH FLOW MODEL
A3: Company Overview
A4: HDFC Bank Limited (HDFC Bank)
A5: Is one of India’s leading private sector banks, providing a wide range of banking and financial services to individuals, businesses, and large corporates across India.
A7: Key Products & Services:
A8: Savings Accounts | Current Accounts | Credit Cards | Personal Loans | Home Loans | Auto Loans | Fixed Deposits |
A9: Business Loans | Insurance & Mutual Fund Distribution | Wealth Management | Digital Banking
A11: Market Position:
A12: One of India's leading private sector banks | Extensive branch and ATM network |
A13: Strong presence across urban, semi-urban and rural India | Wide retail and corporate customer base | Strong digital banking capabilities
A15: Key Assumptions and methodology
A16: Parameter | C16: Value | D16: Rationable
A17: valuation date
A18: Projection period
A19: Revenue growth % | C19: 0.12 | D19: declining PAT growth assumption
A20: Annual Growth tapering | C20: 0.01
A22: Terminal Growth Rate | C22: 0.06 | D22: Conservative long term considering India's GDP
A24: Risk - Free Rate (Rf) | C24: 0.0721 | D24: 10 year Indian government Bond Yield
A25: Equity Risk Premium (ERP) | C25: =14.209%-C24 -> 0.06999 | D25: Expected return over risk free rate of equity investors
A26: Tax Rate | C26: 0.25 | D26: Effective tax rate base on historical data
A30: Financial performance ( ₹ Crores)
A31: INCOME STATEMENT
A32: Particulars | B32: FY22A | C32: FY23A | D32: FY24A | E32: FY25A | F32: FY26A | H32: CAGR
A33: Sales | B33: 135936.41 | C33: 170754.05 | D33: 283649.02 | E33: 336367.43 | F33: 348615.15
A34: % Growth | C34: =C33/B33-1 -> 0.25613182 | D34: =D33/C33-1 -> 0.66115545 | E34: =E33/D33-1 -> 0.1858579 | F34: =F33/E33-1 -> 0.03641173 | H34: =_xlfn.RRI(4,B33,F33) -> 0.26547222
A36: Cost of Goods Sold | B36: =SUM('Data Sheet (2)'!G18,-'Data Sheet (2)'!G19,'Data Sheet (2)'!G20:G21) -> 1772.27 | C36: =SUM('Data Sheet (2)'!H18,-'Data Sheet (2)'!H19,'Data Sheet (2)'!H20:H21) -> 2176.5 | D36: =SUM('Data Sheet (2)'!I18,-'Data Sheet (2)'!I19,'Data Sheet (2)'!I20:I21) -> 3255.75 | E36: =SUM('Data Sheet (2)'!J18,-'Data Sheet (2)'!J19,'Data Sheet (2)'!J20:J21) -> 3943.56 | F36: =SUM('Data Sheet (2)'!K18,-'Data Sheet (2)'!K19,'Data Sheet (2)'!K20:K21) -> 4691.2
A37: % of Revenue | B37: =B36/B33 -> 0.013037493 | C37: =C36/C33 -> 0.012746403 | D37: =D36/D33 -> 0.011478094 | E37: =E36/E33 -> 0.011723965 | F37: =F36/F33 -> 0.013456673
A38: Gross Profit | B38: =B33-B36 -> 134164.14 | C38: =C33-C36 -> 168577.55 | D38: =D33-D36 -> 280393.27 | E38: =E33-E36 -> 332423.87 | F38: =F33-F36 -> 343923.95
A39: Gross Margin % | B39: =B38/B33 -> 0.98696251 | C39: =C38/C33 -> 0.9872536 | D39: =D38/D33 -> 0.98852191 | E39: =E38/E33 -> 0.98827603 | F39: =F38/F33 -> 0.98654333
A40: Operating Expenses | B40: =SUM('Data Sheet (2)'!G22:G24) -> 54784.69 | C40: =SUM('Data Sheet (2)'!H22:H24) -> 60865.8 | D40: =SUM('Data Sheet (2)'!I22:I24) -> 170939.79 | E40: =SUM('Data Sheet (2)'!J22:J24) -> 183030.89 | F40: =SUM('Data Sheet (2)'!K22:K24) -> 198944.03
A41: % of Revenue | B41: =B40/B33 -> 0.40301704 | C41: =C40/C33 -> 0.35645304 | D41: =D40/D33 -> 0.60264545 | E41: =E40/E33 -> 0.54413975 | F41: =F40/F33 -> 0.57066949
A43: EBITDA | B43: =B38-B40 -> 79379.45 | C43: =C38-C40 -> 107711.75 | D43: =D38-D40 -> 109453.48 | E43: =E38-E40 -> 149392.98 | F43: =F38-F40 -> 144979.92
A44: EBITDA Margin % | B44: =B43/B33 -> 0.58394546 | C44: =C43/C33 -> 0.63080056 | D44: =D43/D33 -> 0.38587646 | E44: =E43/E33 -> 0.44413628 | F44: =F43/F33 -> 0.41587384
A46: Depreciation & Amortisation | B46: ='Data Sheet (2)'!G26 -> 1680.73 | C46: ='Data Sheet (2)'!H26 -> 2345.47 | D46: ='Data Sheet (2)'!I26 -> 3092.08 | E46: ='Data Sheet (2)'!J26 -> 3805.23 | F46: ='Data Sheet (2)'!K26 -> 4194.9
A47: % of sales | B47: =B46/B33 -> 0.01236409 | C47: =C46/C33 -> 0.013735955 | D47: =D46/D33 -> 0.010901078 | E47: =E46/E33 -> 0.011312718 | F47: =F46/F33 -> 0.01203304
A48: EBIT | B48: =B43-B46 -> 77698.72 | C48: =C43-C46 -> 105366.28 | D48: =D43-D46 -> 106361.4 | E48: =E43-E46 -> 145587.75 | F48: =F43-F46 -> 140785.02
A49: EBIT Margin % | B49: =B48/B33 -> 0.57158137 | C49: =C48/C33 -> 0.6170646 | D49: =D48/D33 -> 0.37497538 | E49: =E48/E33 -> 0.43282356 | F49: =F48/F33 -> 0.4038408
A51: Other Income | B51: ='Data Sheet (2)'!G25 -> 31758.99 | C51: ='Data Sheet (2)'!H25 -> 33912.05 | D51: ='Data Sheet (2)'!I25 -> 124345.75 | E51: ='Data Sheet (2)'!J25 -> 134548.5 | F51: ='Data Sheet (2)'!K25 -> 146847.66
A52: Interest | B52: ='Data Sheet (2)'!G27 -> 58584.33 | C52: ='Data Sheet (2)'!H27 -> 77779.94 | D52: ='Data Sheet (2)'!I27 -> 154138.55 | E52: ='Data Sheet (2)'!J27 -> 183894.2 | F52: ='Data Sheet (2)'!K27 -> 185491.23
A53: % of debt | B53: =B52/'Data Sheet (2)'!G59 -> 0.032820913 | C53: =C52/'Data Sheet (2)'!H59 -> 0.036359156 | D53: =D52/'Data Sheet (2)'!I59 -> 0.049602064 | E53: =E52/'Data Sheet (2)'!J59 -> 0.054967566 | F53: =F52/'Data Sheet (2)'!K59 -> 0.050294211
A54: Profit Before Tax (PBT) | B54: =B48+B51-B52 -> 50873.38 | C54: =C48+C51-C52 -> 61498.39 | D54: =D48+D51-D52 -> 76568.6 | E54: =E48+E51-E52 -> 96242.05 | F54: =F48+F51-F52 -> 102141.45
A55: PBT Margin % | B55: =B54/B33 -> 0.37424396 | C55: =C54/C33 -> 0.36015772 | D55: =D54/D33 -> 0.26994135 | E55: =E54/E33 -> 0.28612179 | F55: =F54/F33 -> 0.292992
A57: Tax Expense | B57: ='Data Sheet (2)'!G29 -> 12722.48 | C57: ='Data Sheet (2)'!H29 -> 15349.69 | D57: ='Data Sheet (2)'!I29 -> 11122.1 | E57: ='Data Sheet (2)'!J29 -> 22801.88 | F57: ='Data Sheet (2)'!K29 -> 22921.99
A58: % of PBT | B58: =B57/B54 -> 0.25008128 | C58: =C57/C54 -> 0.24959499 | D58: =D57/D54 -> 0.14525667 | E58: =E57/E54 -> 0.23692222 | F58: =F57/F54 -> 0.22441418
A59: Net profit | B59: =B54-B57 -> 38150.9 | C59: =C54-C57 -> 46148.7 | D59: =D54-D57 -> 65446.5 | E59: =E54-E57 -> 73440.17 | F59: =F54-F57 -> 79219.46
A60: Net Profit Margin % | B60: =B59/B33 -> 0.28065255 | C60: =C59/C33 -> 0.27026416 | D60: =D59/D33 -> 0.23073057 | E60: =E59/E33 -> 0.21833318 | F60: =F59/F33 -> 0.22724044
A63: BALANCE SHEET
A64: Particulars | B64: FY22A | C64: FY23A | D64: FY24A | E64: FY25A | F64: FY26A
A65: Equity Share Capital | B65: ='Data Sheet (2)'!G57 -> 554.55 | C65: ='Data Sheet (2)'!H57 -> 557.97 | D65: ='Data Sheet (2)'!I57 -> 759.69 | E65: ='Data Sheet (2)'!J57 -> 765.22 | F65: ='Data Sheet (2)'!K57 -> 1539.34
A66: Reserves | B66: ='Data Sheet (2)'!G58 -> 246771.62 | C66: ='Data Sheet (2)'!H58 -> 288879.53 | D66: ='Data Sheet (2)'!I58 -> 455635.56 | E66: ='Data Sheet (2)'!J58 -> 521024.17 | F66: ='Data Sheet (2)'!K58 -> 584520.13
A67: Borrowings | B67: ='Data Sheet (2)'!G59 -> 1784969.5 | C67: ='Data Sheet (2)'!H59 -> 2139211.9 | D67: ='Data Sheet (2)'!I59 -> 3107502.7 | E67: ='Data Sheet (2)'!J59 -> 3345503.8 | F67: ='Data Sheet (2)'!K59 -> 3688122.8
A68: Other liabilities | B68: ='Data Sheet (2)'!G60 -> 90638.6 | C68: ='Data Sheet (2)'!H60 -> 101783.03 | D68: ='Data Sheet (2)'!I60 -> 466296.27 | E68: ='Data Sheet (2)'!J60 -> 524816.64 | F68: ='Data Sheet (2)'!K60 -> 633519.03
A69: Total | B69: =SUM(B65:B68) -> 2122934.3 | C69: =SUM(C65:C68) -> 2530432.4 | D69: =SUM(D65:D68) -> 4030194.3 | E69: =SUM(E65:E68) -> 4392109.8 | F69: =SUM(F65:F68) -> 4907701.3
A70: Net block | B70: ='Data Sheet (2)'!G62 -> 6432.07 | C70: ='Data Sheet (2)'!H62 -> 8431.35 | D70: ='Data Sheet (2)'!I62 -> 12603.76 | E70: ='Data Sheet (2)'!J62 -> 15257.94 | F70: ='Data Sheet (2)'!K62 -> 16491.59
A71: Capital Work In Progress | B71: ='Data Sheet (2)'!G63 -> 0 | C71: ='Data Sheet (2)'!H63 -> 0 | D71: ='Data Sheet (2)'!I63 -> 0 | E71: ='Data Sheet (2)'!J63 -> 0 | F71: ='Data Sheet (2)'!K63 -> 0
A72: Investment | B72: ='Data Sheet (2)'!G64 -> 449263.86 | C72: ='Data Sheet (2)'!H64 -> 511581.71 | D72: ='Data Sheet (2)'!I64 -> 1005681.6 | E72: ='Data Sheet (2)'!J64 -> 1186472.9 | F72: ='Data Sheet (2)'!K64 -> 1280216.3
A73: Receivables | B73: ='Data Sheet (2)'!G67 -> 0 | C73: ='Data Sheet (2)'!H67 -> 0 | D73: ='Data Sheet (2)'!I67 -> 0 | E73: ='Data Sheet (2)'!J67 -> 0 | F73: ='Data Sheet (2)'!K67 -> 0
A74: Inventory | B74: ='Data Sheet (2)'!G68 -> 0 | C74: ='Data Sheet (2)'!H68 -> 0 | D74: ='Data Sheet (2)'!I68 -> 0 | E74: ='Data Sheet (2)'!J68 -> 0 | F74: ='Data Sheet (2)'!K68 -> 0
A75: Cash and Bank | B75: ='Data Sheet (2)'!G69 -> 130030.71 | C75: ='Data Sheet (2)'!H69 -> 117189.28 | D75: ='Data Sheet (2)'!I69 -> 178718.67 | E75: ='Data Sheet (2)'!J69 -> 144390.25 | F75: ='Data Sheet (2)'!K69 -> 200707.11
A76: Other Asset | B76: ='Data Sheet (2)'!G65-SUM('Data Sheet (2)'!G67,'Data Sheet (2)'!G68,'Data Sheet (2)'!G69) -> 1537207.7 | C76: ='Data Sheet (2)'!H65-SUM('Data Sheet (2)'!H67,'Data Sheet (2)'!H68,'Data Sheet (2)'!H69) -> 1893230.1 | D76: ='Data Sheet (2)'!I65-SUM('Data Sheet (2)'!I67,'Data Sheet (2)'!I68,'Data Sheet (2)'!I69) -> 2833190.2 | E76: ='Data Sheet (2)'!J65-SUM('Data Sheet (2)'!J67,'Data Sheet (2)'!J68,'Data Sheet (2)'!J69) -> 3045988.8 | F76: ='Data Sheet (2)'!K65-SUM('Data Sheet (2)'!K67,'Data Sheet (2)'!K68,'Data Sheet (2)'!K69) -> 3410286.4
A77: Total | B77: =SUM(B70:B76) -> 2122934.3 | C77: =SUM(C70:C76) -> 2530432.4 | D77: =SUM(D70:D76) -> 4030194.3 | E77: =SUM(E70:E76) -> 4392109.8 | F77: =SUM(F70:F76) -> 4907701.3
A80: Revenue projections and Growth Assumptions
A81: Year | B81: FY27E | C81: FY28E | D81: FY29E | E81: FY30E | F81: FY31E
A82: Revenue Growth% | B82: {=CHOOSE($C$84,$B$85:$F$85,B86:$F$86,$B$87:$F$87)} -> 0.12 | C82: 0.11 | D82: 0.1 | E82: 0.09 | F82: 0.08
A83: Revenue(in Crs) | B83: =F33*(1+B82) -> 390448.97 | C83: =B83*(1+C82) -> 433398.35 | D83: =C83*(1+D82) -> 476738.19 | E83: =D83*(1+E82) -> 519644.63 | F83: =E83*(1+F82) -> 561216.2
A84: chosen Scenario | B84: Base year | C84: =MATCH(B84,A85:A87,0) -> 1
A85: Base year | B85: =C19 -> 0.12 | C85: =B85-C20 -> 0.11 | D85: =C85-1% -> 0.1 | E85: =D85-1% -> 0.09 | F85: =E85-1% -> 0.08
A86: Best year | B86: =B85+3% -> 0.15 | C86: =B86-C20 -> 0.14 | D86: =C86-D20 -> 0.14 | E86: =D86-E20 -> 0.14 | F86: =E86-F20 -> 0.14
A87: Worst year | B87: =B85-3% -> 0.09 | C87: =B87-C20 -> 0.08 | D87: =D85-3% -> 0.07 | E87: =E85-3% -> 0.06 | F87: =F85-3% -> 0.05
A90: Free Cash Flow Projections (₹ Crores)
A91: Year | B91: FY27E | C91: FY28E | D91: FY29E | E91: FY30E | F91: FY31E
A92: Revenue | B92: =B83 -> 390448.97 | C92: =C83 -> 433398.35 | D92: =D83 -> 476738.19 | E92: =E83 -> 519644.63 | F92: =F83 -> 561216.2
A93: EBITDA Margin % | B93: =F44 -> 0.41587384 | C93: =B93 -> 0.41587384 | D93: =C93 -> 0.41587384 | E93: =D93 -> 0.41587384 | F93: =E93 -> 0.41587384
A94: EBITDA | B94: =B92*B93 -> 162377.51 | C94: =C92*C93 -> 180239.04 | D94: =D92*D93 -> 198262.94 | E94: =E92*E93 -> 216106.6 | F94: =F92*F93 -> 233395.13
A95: Less: Depreciation | B95: =B92*AVERAGE(B47:F47) -> 4712.4755 | C95: =C92*AVERAGE(C47:G47) -> 5198.9157 | D95: =D92*AVERAGE(D47:H47) -> 5442.2582 | E95: =E92*AVERAGE(E47:I47) -> 6065.7489 | F95: =F92*AVERAGE(F47:J47) -> 6753.1369
A96: EBIT | B96: =B94-B95 -> 157665.03 | C96: =C94-C95 -> 175040.12 | D96: =D94-D95 -> 192820.68 | E96: =E94-E95 -> 210040.86 | F96: =F94-F95 -> 226642
A97: NOPAT=EBIT*(1-Tax Rate) | B97: =B96*(1-Tax_rate) -> 118248.78 | C97: =C96*(1-Tax_rate) -> 131280.09 | D97: =D96*(1-Tax_rate) -> 144615.51 | E97: =E96*(1-Tax_rate) -> 157530.64 | F97: =F96*(1-Tax_rate) -> 169981.5
A98: Add: Depreciation | B98: =B95 -> 4712.4755 | C98: =C95 -> 5198.9157 | D98: =D95 -> 5442.2582 | E98: =E95 -> 6065.7489 | F98: =F95 -> 6753.1369
A99: Less:Reinvestment | B99: =B97*50% -> 59124.388 | C99: =C97*50% -> 65640.045 | D99: =D97*50% -> 72307.756 | E99: =E97*50% -> 78765.321 | F99: =F97*50% -> 84990.749
A100: Free Cash Flow to Firm | B100: =B97+B98-B99 -> 63836.864 | C100: =C97+C98-C99 -> 70838.961 | D100: =D97+D98-D99 -> 77750.014 | E100: =E97+E98-E99 -> 84831.07 | F100: =F97+F98-F99 -> 91743.885
A102: WACC Calculation
A103: Target Capital Structure
A104: Proportion of debt | B104: ='comparable companies Analysis'!E17 -> 0.74567352
A105: Proportion of Equity | B105: =1-B104 -> 0.25432648
A107: Current Capital Structure
A108: Market Cap | B108: ='comparable companies Analysis'!E3 -> 1111989.2
A109: Total Debt | B109: ='comparable companies Analysis'!H3 -> 3733201.9
A110: Debt/Equity | B110: =B109/B108 -> 3.3572285
A112: Cost of debt
A113: Pre-Tax Cost of Debt | B113: 0.0675
A114: Tax Ratio | B114: =Tax_rate -> 0.25
A115: After -Tax Cost of Debt | B115: =B113*(1-B114) -> 0.050625
A117: Cost of equity
A118: Risk free Rate | B118: =C24 -> 0.0721
A119: Equity Risk premium | B119: =C25 -> 0.06999
A120: Levered Equity Beta | B120: ='comparable companies Analysis'!H17*(1+'DCF model'!B110)*(1-Tax_rate) -> 0.61079584
A121: Cost of equity | B121: =B118+B120*B119 -> 0.1148496
A122: WACC | B122: =(B121*B105)+(B115*B104) -> 0.066959017
A125: Terminal Value Calculation
A126: Terminal Year FCF (FY31) | B126: =F100 -> 91743.885
...

Sheet comparable companies Analysis
A1: COMPANIES DATA
A2: S.No. | B2: Company | C2: CMP Rs. | D2: P/E | E2: Mar Cap Rs.Cr. | F2: Sales Rs.Cr. | G2: EPS 12M Rs. | H2: Debt Rs.Cr. | I2: EV / EBITDA | J2: EV Rs.Cr. | K2: IV Rs. | L2: beta | M2: Cash Equivalents | N2: NP(Cr)
A3: 1 | B3: HDFC Bank | C3: 721.2 | D3: 14.07 | E3: 1111989.2 | F3: 351818.61 | G3: 51.35 | H3: 3733201.9 | I3: 15.97 | J3: 4694611.4 | K3: 747.71 | L3: 0.92 | M3: 150579.79 | N3: 82511.72
A4: 2 | B4: ICICI Bank | C4: 1310.6 | D4: 16.77 | E4: 940846.48 | F4: 198379.35 | G4: 78.36 | H4: 2096680.5 | I4: 17.65 | J4: 2963517.9 | K4: 1020.15 | L4: 0.99 | M4: 74009.08 | N4: 59756.14
A5: 3 | B5: Kotak Mah. Bank | C5: 418.35 | D5: 20.78 | E5: 416169.61 | F5: 70887.47 | G5: 20.41 | H5: 662333.86 | I5: 18.06 | J5: 1027221.7 | K5: 305.85 | L5: 0.89 | M5: 51281.74 | N5: 20296.17
A6: 4 | B6: Axis Bank | C6: 1217.1 | D6: 13.64 | E6: 378967.18 | F6: 135731.89 | G6: 89.39 | H6: 1656431.1 | I6: 17.92 | J6: 1976741.4 | K6: 1112.66 | L6: 1.03 | M6: 58656.85 | N6: 27938.79
A7: 5 | B7: IDBI Bank | C7: 86.57 | D7: 9.99 | E7: 93083.55 | F7: 29542.24 | G7: 8.67 | H7: 374879.89 | I7: 15.75 | J7: 434732.97 | K7: 88.01 | L7: 0.9 | M7: 33230.47 | N7: 9343.31
A9: INDUSTRY DATA
A10: Company | B10: Equity value | C10: Total Debt | D10: Debt/Equity | E10: Debt/Capital | F10: Tax rate % | G10: Levered beta | H10: Unlevered beta
A11: ICICI Bank | B11: =E4 -> 940846.48 | C11: =H4 -> 2096680.5 | D11: =C11/B11 -> 2.2285043 | E11: =C11/(B11+C11) -> 0.69025905 | F11: =Tax_rate -> 0.25 | G11: =L4 -> 0.99 | H11: =G11/(1+D11)*(1-Tax_rate) -> 0.22998266
A12: Kotak Mah. Bank | B12: =E5 -> 416169.61 | C12: =H5 -> 662333.86 | D12: =C12/B12 -> 1.5914998 | E12: =C12/(B12+C12) -> 0.61412307 | F12: =Tax_rate -> 0.25 | G12: =L5 -> 0.89 | H12: =G12/(1+D12)*(1-Tax_rate) -> 0.25757285
A13: Axis Bank | B13: =E6 -> 378967.18 | C13: =H6 -> 1656431.1 | D13: =C13/B13 -> 4.370909 | E13: =C13/(B13+C13) -> 0.81381178 | F13: =Tax_rate -> 0.25 | G13: =L6 -> 1.03 | H13: =G13/(1+D13)*(1-Tax_rate) -> 0.1438304
A14: IDBI Bank | B14: =E7 -> 93083.55 | C14: =H7 -> 374879.89 | D14: =C14/B14 -> 4.0273484 | E14: =C14/(B14+C14) -> 0.80108799 | F14: =Tax_rate -> 0.25 | G14: =L7 -> 0.9 | H14: =G14/(1+D14)*(1-Tax_rate) -> 0.13426561
A16: Average | D16: =AVERAGE(D11:D14) -> 3.0545654 | E16: =AVERAGE(E11:E14) -> 0.72982047 | F16: =AVERAGE(F11:F14) -> 0.25 | G16: =AVERAGE(G11:G14) -> 0.9525 | H16: =AVERAGE(H11:H14) -> 0.19141288
A17: Median | D17: =MEDIAN(D11:D14) -> 3.1279264 | E17: =MEDIAN(E11:E14) -> 0.74567352 | F17: =MEDIAN(F11:J14) -> 0.25 | G17: =MEDIAN(G11:K14) -> 0.57378643 | H17: =MEDIAN(H11:H14) -> 0.18690653
A21: COMPAREABLE COMPANIES ANALYSIS
B22: Market Data | I22: Financial Data | K22: Valuation
A23: Company name | B23: price(per share) | C23: Shares | D23: Market cap(₹ Cr) | E23: Debt | F23: Cash & Equivalents | G23: EV (₹cr) | H23: Sales (₹cr) | I23: EBITDA(₹ Cr) | J23: Earnings (₹ Cr) | K23: EV/Sales (X) | L23: EV / EBITDA(X) | M23: P/E(X)
A24: ICICI Bank | B24: =C4 -> 1310.6 | C24: =D24/B24 -> 717.87462 | D24: =E4 -> 940846.48 | E24: =H4 -> 2096680.5 | F24: =M4 -> 74009.08 | G24: =D24+E24-F24 -> 2963517.9 | H24: =F4 -> 198379.35 | I24: =J4/I4 -> 167904.69 | J24: =N4 -> 59756.14 | K24: =G24/H24 -> 14.938641 | L24: =G24/I24 -> 17.65 | M24: =D24/J24 -> 15.744767
A25: Kotak Mah. Bank | B25: =C5 -> 418.35 | C25: =D25/B25 -> 994.78812 | D25: =E5 -> 416169.61 | E25: =H5 -> 662333.86 | F25: =M5 -> 51281.74 | G25: =D25+E25-F25 -> 1027221.7 | H25: =F5 -> 70887.47 | I25: =J5/I5 -> 56878.28 | J25: =N5 -> 20296.17 | K25: =G25/H25 -> 14.490879 | L25: =G25/I25 -> 18.06 | M25: =D25/J25 -> 20.504835
A26: Axis Bank | B26: =C6 -> 1217.1 | C26: =D26/B26 -> 311.36898 | D26: =E6 -> 378967.18 | E26: =H6 -> 1656431.1 | F26: =M6 -> 58656.85 | G26: =D26+E26-F26 -> 1976741.4 | H26: =F6 -> 135731.89 | I26: =J6/I6 -> 110309.23 | J26: =N6 -> 27938.79 | K26: =G26/H26 -> 14.563574 | L26: =G26/I26 -> 17.92 | M26: =D26/J26 -> 13.564194
A27: IDBI Bank | B27: =C7 -> 86.57 | C27: =D27/B27 -> 1075.2403 | D27: =E7 -> 93083.55 | E27: =H7 -> 374879.89 | F27: =M7 -> 33230.47 | G27: =D27+E27-F27 -> 434732.97 | H27: =F7 -> 29542.24 | I27: =J7/I7 -> 27602.093 | J27: =N7 -> 9343.31 | K27: =G27/H27 -> 14.71564 | L27: =G27/I27 -> 15.75 | M27: =D27/J27 -> 9.9625882
A29: Average | K29: =AVERAGE(K24:K27) -> 14.677183 | L29: =AVERAGE(L24:L27) -> 17.345 | M29: =AVERAGE(M24:M27) -> 14.944096
A30: Median | K30: =MEDIAN(K24:K27) -> 14.639607 | L30: =MEDIAN(L24:L27) -> 17.785 | M30: =MEDIAN(M24:M27) -> 14.654481
A32: HDFC BANK | B32: =C3 -> 721.2 | C32: =D32/B32 -> 1541.8597 | D32: =E3 -> 1111989.2 | E32: =H3 -> 3733201.9 | F32: =M3 -> 150579.79 | G32: =D32+E32-F32 -> 4694611.4 | H32: =F3 -> 351818.61 | I32: =J3/I3 -> 293964.39 | J32: =N3 -> 82511.72 | K32: =G32/H32 -> 13.34384 | L32: =G32/I32 -> 15.97 | M32: =D32/J32 -> 13.476743
A35: Metric | B35: Comps | C35: EV | D35: Net Debt | E35: Equity Value | F35: Shares | G35: Shares Price
A36: EV/Sales | B36: {=TRANSPOSE(K30:M30)} -> 14.639607 | C36: =H32*B36 -> 5150486.1 | D36: =$E$32-F32 -> 3582622.1 | E36: =C36-D36 -> 1567864 | F36: =$C$32 -> 1541.8597 | G36: =E36/F36 -> 1016.8655
A37: EV/EBITDA | B37: 17.785 | C37: =I32*B37 -> 5228156.8 | D37: =$E$32-F32 -> 3582622.1 | E37: =C37-D37 -> 1645534.6 | F37: =$C$32 -> 1541.8597 | G37: =E37/F37 -> 1067.2402
A38: P/E Ratio | B38: 14.654481 | C38: =E38+D38 -> 4791788.5 | D38: =$E$32-F32 -> 3582622.1 | E38: =B38*J32 -> 1209166.4 | F38: =$C$32 -> 1541.8597 | G38: =E38/F38 -> 784.22594
